{
  "nightly": {
    "description": "Unstable",
    "hide": false,
    "last_updated": "2024-10-10T00:47:39.000Z",
    "last_updated_url": "https://github.com/hotio/stash/actions/runs/11265365455",
    "latest": false,
    "tags": [
      "nightly",
      "nightly-b6db4c31ca689cfb8b9054e493c94c80abc24f80",
      "nightly-bcb3782"
    ]
  },
  "release": {
    "description": "Releases",
    "hide": false,
    "last_updated": "2024-09-25T05:25:51.000Z",
    "last_updated_url": "https://github.com/hotio/stash/actions/runs/11026725563",
    "latest": true,
    "tags": [
      "release",
      "release-0.27.0",
      "release-de32d1d"
    ]
  }
}
